genfunc/__init__.py
genfunc/core/__init__.py
genfunc/core/config.py
genfunc/core/generator.py
genfunc/core/utils.py
genfunc/core/llm_providers/__init__.py
genfunc/core/llm_providers/anthropic_provider.py
genfunc/core/llm_providers/base.py
genfunc/core/llm_providers/openai_provider.py
genfunc-0.1.0.dist-info/METADATA
genfunc-0.1.0.dist-info/WHEEL
genfunc-0.1.0.dist-info/licenses/LICENSE
genfunc-0.1.0.dist-info/RECORD
