Metadata-Version: 2.3
Name: genfunc
Version: 0.1.0
Summary: A Python package for generating functions using LLMs
Project-URL: Homepage, https://github.com/argishh/genfunc
Project-URL: Bug Tracker, https://github.com/argishh/genfunc/issues
Author-email: Argish <argish.official@gmail.com>
Classifier: License :: OSI Approved :: MIT License
Classifier: Operating System :: OS Independent
Classifier: Programming Language :: Python :: 3
Requires-Python: >=3.8
Requires-Dist: anthropic>=0.40.0
Requires-Dist: openai>=1.56.0
Requires-Dist: python-dotenv>=0.10.0
